odoo/addons/l10n_it_ricevute_bancarie/README.rst
odoo/addons/l10n_it_ricevute_bancarie/__init__.py
odoo/addons/l10n_it_ricevute_bancarie/__manifest__.py
odoo/addons/l10n_it_ricevute_bancarie/data/riba_sequence.xml
odoo/addons/l10n_it_ricevute_bancarie/demo/riba_demo.xml
odoo/addons/l10n_it_ricevute_bancarie/i18n/it.po
odoo/addons/l10n_it_ricevute_bancarie/i18n/l10n_it_ricevute_bancarie.pot
odoo/addons/l10n_it_ricevute_bancarie/migrations/12.0.1.6.1/post-migrate.py
odoo/addons/l10n_it_ricevute_bancarie/models/__init__.py
odoo/addons/l10n_it_ricevute_bancarie/models/account_config.py
odoo/addons/l10n_it_ricevute_bancarie/models/riba.py
odoo/addons/l10n_it_ricevute_bancarie/models/riba_config.py
odoo/addons/l10n_it_ricevute_bancarie/models/account/__init__.py
odoo/addons/l10n_it_ricevute_bancarie/models/account/account.py
odoo/addons/l10n_it_ricevute_bancarie/models/account/bank_statement.py
odoo/addons/l10n_it_ricevute_bancarie/models/partner/__init__.py
odoo/addons/l10n_it_ricevute_bancarie/models/partner/partner.py
odoo/addons/l10n_it_ricevute_bancarie/readme/CONFIGURE.rst
odoo/addons/l10n_it_ricevute_bancarie/readme/CONTRIBUTORS.rst
odoo/addons/l10n_it_ricevute_bancarie/readme/DESCRIPTION.rst
odoo/addons/l10n_it_ricevute_bancarie/readme/USAGE.rst
odoo/addons/l10n_it_ricevute_bancarie/report/__init__.py
odoo/addons/l10n_it_ricevute_bancarie/report/distinta_qweb.py
odoo/addons/l10n_it_ricevute_bancarie/report/report.xml
odoo/addons/l10n_it_ricevute_bancarie/security/ir.model.access.csv
odoo/addons/l10n_it_ricevute_bancarie/security/riba_security.xml
odoo/addons/l10n_it_ricevute_bancarie/static/description/icon.png
odoo/addons/l10n_it_ricevute_bancarie/static/description/index.html
odoo/addons/l10n_it_ricevute_bancarie/tests/__init__.py
odoo/addons/l10n_it_ricevute_bancarie/tests/riba_common.py
odoo/addons/l10n_it_ricevute_bancarie/tests/test_riba.py
odoo/addons/l10n_it_ricevute_bancarie/views/account_config_view.xml
odoo12_addon_l10n_it_ricevute_bancarie-12.0.1.9.0.dist-info/METADATA
odoo12_addon_l10n_it_ricevute_bancarie-12.0.1.9.0.dist-info/WHEEL
odoo12_addon_l10n_it_ricevute_bancarie-12.0.1.9.0.dist-info/top_level.txt
odoo12_addon_l10n_it_ricevute_bancarie-12.0.1.9.0.dist-info/RECORD
