Metadata-Version: 2.1
Name: odoo12-addon-l10n-it-ricevute-bancarie
Version: 12.0.1.9.0
Summary: Ricevute bancarie
Home-page: https://github.com/OCA/l10n-italy/tree/12.0/l10n_it_ricevute_bancarie
Author: Odoo Community Association (OCA)
Author-email: support@odoo-community.org
License: AGPL-3
Platform: UNKNOWN
Classifier: Programming Language :: Python
Classifier: Framework :: Odoo
Classifier: Framework :: Odoo :: 12.0
Classifier: License :: OSI Approved :: GNU Affero General Public License v3
Requires-Python: >=3.5
Requires-Dist: odoo12-addon-account-due-list
Requires-Dist: odoo12-addon-account-group-menu
Requires-Dist: odoo12-addon-l10n-it-abicab
Requires-Dist: odoo12-addon-l10n-it-fatturapa-out
Requires-Dist: odoo12-addon-l10n-it-fiscalcode
Requires-Dist: odoo (<12.1dev,>=12.0a)
